pygna/_KS_test.py
pygna/__init__.py
pygna/block_model.py
pygna/centrality.py
pygna/cli.py
pygna/command.py
pygna/converters.py
pygna/degree_model.py
pygna/diagnostic.py
pygna/elaborators.py
pygna/output.py
pygna/painter.py
pygna/plots.py
pygna/reading_class.py
pygna/statistical_comparison.py
pygna/statistical_diffusion.py
pygna/statistical_test.py
pygna/utils.py
pygna-3.3.1.dist-info/LICENSE
pygna-3.3.1.dist-info/METADATA
pygna-3.3.1.dist-info/WHEEL
pygna-3.3.1.dist-info/entry_points.txt
pygna-3.3.1.dist-info/top_level.txt
pygna-3.3.1.dist-info/RECORD
