Metadata-Version: 2.1
Name: pygna
Version: 3.3.1
Summary: Geneset Network Analysis
Home-page: https://github.com/stracquadaniolab/pygna
Author: Viola Fanfani, Giovanni Stracquadanio
Author-email: v.fanfani@sms.ed.ac.uk
License: MIT
Keywords: Bioinformatics Network Statistics
Platform: UNKNOWN
Classifier: License :: OSI Approved :: MIT License
Classifier: Programming Language :: Python :: 3.8
Classifier: Topic :: Scientific/Engineering :: Bio-Informatics
Requires-Python: >=3.8
Requires-Dist: pandas
Requires-Dist: numpy
Requires-Dist: scipy
Requires-Dist: matplotlib
Requires-Dist: pyyaml
Requires-Dist: tables (>=3.4.4)
Requires-Dist: seaborn (>=0.9)
Requires-Dist: palettable
Requires-Dist: networkx (==2.3)
Requires-Dist: statsmodels
Requires-Dist: argh
Requires-Dist: mygene
